inmanta_plugins/redhat/__init__.py
inmanta_plugins/redhat/setup.cfg
inmanta_plugins/redhat/model/_init.cf
inmanta_module_redhat-1.0.10.dist-info/METADATA
inmanta_module_redhat-1.0.10.dist-info/WHEEL
inmanta_module_redhat-1.0.10.dist-info/top_level.txt
inmanta_module_redhat-1.0.10.dist-info/RECORD
