Metadata-Version: 2.1
Name: inmanta-module-redhat
Version: 1.0.10
License: Apache 2.0
Requires-Dist: inmanta-module-std
